LICENSE
MANIFEST.in
README.rst
setup.cfg
setup.py
django_ttdb.egg-info/PKG-INFO
django_ttdb.egg-info/SOURCES.txt
django_ttdb.egg-info/dependency_links.txt
django_ttdb.egg-info/requires.txt
django_ttdb.egg-info/top_level.txt
tests/migrations/0001_initial.py
tests/migrations/__init__.py
ttdb/__init__.py
ttdb/decorators.py
ttdb/runner.py
ttdb/testcases.py
ttdb/utils.py