Metadata-Version: 1.1
Name: django-ttdb
Version: 0.4
Summary: Creates a django test database using a postgres template database.
Home-page: http://github.com/wilbuick/django-ttdb
Author: William Buick
Author-email: william.buick@encode.net.nz
License: BSD
Platform: UNKNOWN
Classifier: Development Status :: 3 - Alpha
Classifier: Environment :: Web Environment
Classifier: Framework :: Django
Classifier: Intended Audience :: Developers
Classifier: License :: OSI Approved :: BSD License
Classifier: Operating System :: OS Independent
Classifier: Programming Language :: Python
Classifier: Programming Language :: Python :: 2.6
Classifier: Programming Language :: Python :: 2.7
Classifier: Programming Language :: Python :: 3.2
Classifier: Programming Language :: Python :: 3.3
